tests
azoth
