Metadata-Version: 1.1
Name: azoth
Version: 0.3.0
Summary: Sqlalchemy utilities
Home-page: https://github.com/TakesxiSximada/azoth
Author: TakesxiSximada
Author-email: takesxi.sximada@gmail.com
License: BSD
Download-URL: https://github.com/TakesxiSximada/azoth
Platform: any
Classifier: Development Status :: 1 - Planning
Classifier: Environment :: Web Environment :: Mozilla
Classifier: Intended Audience :: Developers
Classifier: Intended Audience :: Information Technology
Classifier: Intended Audience :: System Administrators
Classifier: License :: OSI Approved :: BSD License
Classifier: Natural Language :: English
Classifier: Natural Language :: Esperanto
Classifier: Natural Language :: Japanese
Classifier: Operating System :: MacOS :: MacOS X
Classifier: Operating System :: Microsoft :: Windows
Classifier: Operating System :: POSIX
Classifier: Programming Language :: Python :: 2.7
Classifier: Programming Language :: Python :: 3.4
